{
  "audiovisual_files": {
    "ee00e0eb-713b-4f53-be20-f757fc7ecaaf": {
      "label": "Encuentro de Tambores",
      "is_offline": false,
      "file_type": "Video",
      "file_url": "https://www.youtube.com/live/f355p8sBuYw?si=WajHURvDGxJvS35j",
      "duration": 10739
    }
  },
  "auto_generate_web_page": true,
  "label": "Bomba Festivals: 2022 Encuentro de Tambores",
  "created_at": "2026-03-04T05:31:15.979Z",
  "created_by": "raymondhyser",
  "updated_at": "2026-03-04T05:31:15.979Z",
  "updated_by": "raymondhyser"
}